gospelo_md2pdf/__init__.py
gospelo_md2pdf/__main__.py
gospelo_md2pdf/cli.py
gospelo_md2pdf/converter.py
gospelo_md2pdf/images.py
gospelo_md2pdf/mermaid.py
gospelo_md2pdf/styles.py
gospelo_md2pdf/styles/default.css
gospelo_md2pdf-1.3.0.dist-info/licenses/LICENSE
gospelo_md2pdf-1.3.0.dist-info/METADATA
gospelo_md2pdf-1.3.0.dist-info/WHEEL
gospelo_md2pdf-1.3.0.dist-info/entry_points.txt
gospelo_md2pdf-1.3.0.dist-info/top_level.txt
gospelo_md2pdf-1.3.0.dist-info/RECORD
