Metadata-Version: 2.4
Name: gospelo-md2pdf
Version: 1.3.0
Summary: Convert Markdown to PDF with Japanese support and MermaidJS diagrams
Author-email: NoStudio LLC <goro-hayakawa@no-studio.net>
License-Expression: MIT
Project-URL: Homepage, https://github.com/gorosun/gospelo-md2pdf
Project-URL: Documentation, https://github.com/gorosun/gospelo-md2pdf#readme
Project-URL: Repository, https://github.com/gorosun/gospelo-md2pdf.git
Project-URL: Issues, https://github.com/gorosun/gospelo-md2pdf/issues
Keywords: markdown,pdf,mermaid,japanese,documentation,converter,weasyprint
Classifier: Development Status :: 4 - Beta
Classifier: Environment :: Console
Classifier: Intended Audience :: Developers
Classifier: Operating System :: OS Independent
Classifier: Programming Language :: Python :: 3
Classifier: Programming Language :: Python :: 3.10
Classifier: Programming Language :: Python :: 3.11
Classifier: Programming Language :: Python :: 3.12
Classifier: Topic :: Documentation
Classifier: Topic :: Text Processing :: Markup :: Markdown
Requires-Python: >=3.10
License-File: LICENSE
Requires-Dist: weasyprint>=60.0
Requires-Dist: markdown>=3.5.0
Provides-Extra: dev
Requires-Dist: pytest>=7.0.0; extra == "dev"
Requires-Dist: pytest-cov>=4.0.0; extra == "dev"
Requires-Dist: black>=23.0.0; extra == "dev"
Requires-Dist: isort>=5.12.0; extra == "dev"
Requires-Dist: mypy>=1.0.0; extra == "dev"
Dynamic: license-file
